{
  "assetCategories": {
    "surface": {
      "metal": {
        "corrugated": {},
        "sheet": {}
      }
    }
  },
  "averageColor": "#000000",
  "categories": [
    "surface",
    "misc"
  ],
  "comp_version": 1,
  "description": "",
  "displacementBias": 0.08641,
  "displacementCalibrationAccuracy": 0.984559,
  "displacementScale": 3.816029,
  "environment": {
    "biome": "undefined",
    "region": "Europe"
  },
  "highest_available_res": 8192,
  "id": "tmnobhhya",
  "json": {
    "contentLength": 12401,
    "uri": "tmnobhhya.json"
  },
  "maps": [
    {
      "averageColor": "#E2E2E2",
      "bitDepth": 32,
      "colorSpace": "sRGB",
      "contentLength": 64719052,
      "maxIntensity": 255,
      "mimeType": "image/x-exr",
      "minIntensity": 0,
      "name": "AO",
      "physicalSize": "2x2",
      "resolution": "8192x8192",
      "type": "ao",
      "uri": "tmnobhhya_8K_AO.exr"
    },
    {
      "averageColor": "#E2E2E2",
      "bitDepth": 8,
      "colorSpace": "sRGB",
      "contentLength": 20428511,
      "maxIntensity": 255,
      "mimeType": "image/jpeg",
      "minIntensity": 0,
      "name": "AO",
      "physicalSize": "2x2",
      "resolution": "8192x8192",
      "type": "ao",
      "uri": "tmnobhhya_8K_AO.jpg"
    },
    {
      "averageColor": "#4A4743",
      "bitDepth": 16,
      "colorSpace": "sRGB",
      "contentLength": 240814516,
      "maxIntensity": 105,
      "mimeType": "image/x-exr",
      "minIntensity": 46,
      "name": "Basecolor",
      "physicalSize": "2x2",
      "resolution": "8192x8192",
      "type": "basecolor",
      "uri": "tmnobhhya_8K_Basecolor.exr"
    },
    {
      "averageColor": "#4A4743",
      "bitDepth": 8,
      "colorSpace": "sRGB",
      "contentLength": 38257534,
      "maxIntensity": 105,
      "mimeType": "image/jpeg",
      "minIntensity": 46,
      "name": "Basecolor",
      "physicalSize": "2x2",
      "resolution": "8192x8192",
      "type": "basecolor",
      "uri": "tmnobhhya_8K_Basecolor.jpg"
    },
    {
      "averageColor": "#808080",
      "bitDepth": 32,
      "colorSpace": "Linear",
      "contentLength": 176404994,
      "maxIntensity": 255,
      "mimeType": "image/x-exr",
      "minIntensity": 0,
      "name": "Bump",
      "physicalSize": "2x2",
      "resolution": "8192x8192",
      "type": "bump",
      "uri": "tmnobhhya_8K_Bump.exr"
    },
    {
      "averageColor": "#808080",
      "bitDepth": 8,
      "colorSpace": "Linear",
      "contentLength": 11881325,
      "maxIntensity": 255,
      "mimeType": "image/jpeg",
      "minIntensity": 0,
      "name": "Bump",
      "physicalSize": "2x2",
      "resolution": "8192x8192",
      "type": "bump",
      "uri": "tmnobhhya_8K_Bump.jpg"
    },
    {
      "averageColor": "#FFFFFF",
      "bitDepth": 32,
      "colorSpace": "sRGB",
      "contentLength": 209529421,
      "maxIntensity": 255,
      "mimeType": "image/x-exr",
      "minIntensity": 255,
      "name": "Cavity",
      "physicalSize": "2x2",
      "resolution": "8192x8192",
      "type": "cavity",
      "uri": "tmnobhhya_8K_Cavity.exr"
    },
    {
      "averageColor": "#FFFFFF",
      "bitDepth": 8,
      "colorSpace": "sRGB",
      "contentLength": 40185349,
      "maxIntensity": 255,
      "mimeType": "image/jpeg",
      "minIntensity": 255,
      "name": "Cavity",
      "physicalSize": "2x2",
      "resolution": "8192x8192",
      "type": "cavity",
      "uri": "tmnobhhya_8K_Cavity.jpg"
    },
    {
      "averageColor": "#838383",
      "bitDepth": 32,
      "colorSpace": "Linear",
      "contentLength": 230106969,
      "maxIntensity": 156,
      "mimeType": "image/x-exr",
      "minIntensity": 119,
      "name": "Displacement",
      "physicalSize": "2x2",
      "resolution": "8192x8192",
      "type": "displacement",
      "uri": "tmnobhhya_8K_Displacement.exr"
    },
    {
      "averageColor": "#838383",
      "bitDepth": 8,
      "colorSpace": "Linear",
      "contentLength": 6137328,
      "maxIntensity": 156,
      "mimeType": "image/jpeg",
      "minIntensity": 119,
      "name": "Displacement",
      "physicalSize": "2x2",
      "resolution": "8192x8192",
      "type": "displacement",
      "uri": "tmnobhhya_8K_Displacement.jpg"
    },
    {
      "averageColor": "#1C1C1C",
      "bitDepth": 32,
      "colorSpace": "Linear",
      "contentLength": 96393284,
      "maxIntensity": 63,
      "mimeType": "image/x-exr",
      "minIntensity": 4,
      "name": "Gloss",
      "physicalSize": "2x2",
      "resolution": "8192x8192",
      "type": "gloss",
      "uri": "tmnobhhya_8K_Gloss.exr"
    },
    {
      "averageColor": "#1C1C1C",
      "bitDepth": 8,
      "colorSpace": "Linear",
      "contentLength": 38552725,
      "maxIntensity": 63,
      "mimeType": "image/jpeg",
      "minIntensity": 4,
      "name": "Gloss",
      "physicalSize": "2x2",
      "resolution": "8192x8192",
      "type": "gloss",
      "uri": "tmnobhhya_8K_Gloss.jpg"
    },
    {
      "averageColor": "#827CE8",
      "bitDepth": 16,
      "colorSpace": "Linear",
      "contentLength": 186171315,
      "maxIntensity": 211,
      "mimeType": "image/x-exr",
      "minIntensity": 56,
      "name": "Normal",
      "physicalSize": "2x2",
      "resolution": "8192x8192",
      "type": "normal",
      "uri": "tmnobhhya_8K_Normal.exr"
    },
    {
      "averageColor": "#827CE8",
      "bitDepth": 8,
      "colorSpace": "Linear",
      "contentLength": 53219437,
      "maxIntensity": 211,
      "mimeType": "image/jpeg",
      "minIntensity": 56,
      "name": "Normal",
      "physicalSize": "2x2",
      "resolution": "8192x8192",
      "type": "normal",
      "uri": "tmnobhhya_8K_Normal.jpg"
    },
    {
      "averageColor": "#E3E3E3",
      "bitDepth": 32,
      "colorSpace": "Linear",
      "contentLength": 93845467,
      "maxIntensity": 251,
      "mimeType": "image/x-exr",
      "minIntensity": 192,
      "name": "Roughness",
      "physicalSize": "2x2",
      "resolution": "8192x8192",
      "type": "roughness",
      "uri": "tmnobhhya_8K_Roughness.exr"
    },
    {
      "averageColor": "#E3E3E3",
      "bitDepth": 8,
      "colorSpace": "Linear",
      "contentLength": 36737047,
      "maxIntensity": 251,
      "mimeType": "image/jpeg",
      "minIntensity": 192,
      "name": "Roughness",
      "physicalSize": "2x2",
      "resolution": "8192x8192",
      "type": "roughness",
      "uri": "tmnobhhya_8K_Roughness.jpg"
    },
    {
      "averageColor": "#383838",
      "bitDepth": 16,
      "colorSpace": "sRGB",
      "contentLength": 220816643,
      "maxIntensity": 56,
      "mimeType": "image/x-exr",
      "minIntensity": 56,
      "name": "Specular",
      "physicalSize": "2x2",
      "resolution": "8192x8192",
      "type": "specular",
      "uri": "tmnobhhya_8K_Specular.exr"
    },
    {
      "averageColor": "#383838",
      "bitDepth": 8,
      "colorSpace": "sRGB",
      "contentLength": 22616904,
      "maxIntensity": 56,
      "mimeType": "image/jpeg",
      "minIntensity": 56,
      "name": "Specular",
      "physicalSize": "2x2",
      "resolution": "8192x8192",
      "type": "specular",
      "uri": "tmnobhhya_8K_Specular.jpg"
    }
  ],
  "meta": [
    {
      "key": "scanArea",
      "name": "Scan Area",
      "value": "2x2 m"
    },
    {
      "key": "height",
      "name": "Height",
      "value": "0.029 m"
    },
    {
      "key": "tileable",
      "name": "Tileable",
      "value": false
    },
    {
      "key": "texelDensity",
      "name": "Texel Density",
      "value": "4096 px/m"
    },
    {
      "key": "calibration",
      "name": "Calibration",
      "value": "GretagMacbeth ColorChecker Color Rendition Chart"
    },
    {
      "key": "scanner",
      "name": "Scanner",
      "value": "MKX"
    }
  ],
  "models": [],
  "name": "Garage Door",
  "pack": {
    "_id": "industrial-metals",
    "name": "Industrial Metals"
  },
  "physicalSize": null,
  "points": 2,
  "previews": {
    "images": [
      {
        "contentLength": 229360,
        "resolution": "360x360",
        "tags": [
          "thumb"
        ],
        "uri": "tmnobhhya_Grid_360.png"
      },
      {
        "contentLength": 308748,
        "resolution": "420x420",
        "tags": [
          "thumb"
        ],
        "uri": "tmnobhhya_Grid_420.png"
      },
      {
        "contentLength": 906028,
        "resolution": "720x720",
        "tags": [
          "thumb",
          "retina"
        ],
        "uri": "tmnobhhya_Grid_720.png"
      },
      {
        "contentLength": 1229826,
        "resolution": "840x840",
        "tags": [
          "thumb",
          "retina"
        ],
        "uri": "tmnobhhya_Grid_840.png"
      },
      {
        "contentLength": 2556010,
        "resolution": "1440x768",
        "tags": [
          "preview",
          "clay"
        ],
        "uri": "tmnobhhya_PopupClay_1440.png"
      },
      {
        "contentLength": 4800220,
        "resolution": "1920x1080",
        "tags": [
          "preview",
          "clay"
        ],
        "uri": "tmnobhhya_PopupClay_1920.png"
      },
      {
        "contentLength": 10316306,
        "resolution": "2880x1536",
        "tags": [
          "preview",
          "clay",
          "retina"
        ],
        "uri": "tmnobhhya_PopupClay_2880.png"
      },
      {
        "contentLength": 19658385,
        "resolution": "3840x2160",
        "tags": [
          "preview",
          "clay",
          "retina"
        ],
        "uri": "tmnobhhya_PopupClay_3840.png"
      },
      {
        "contentLength": 2678206,
        "resolution": "1440x768",
        "tags": [
          "preview",
          "tiled"
        ],
        "uri": "tmnobhhya_PopupTiled_1440.png"
      },
      {
        "contentLength": 4937615,
        "resolution": "1920x1080",
        "tags": [
          "preview",
          "tiled"
        ],
        "uri": "tmnobhhya_PopupTiled_1920.png"
      },
      {
        "contentLength": 10412414,
        "resolution": "2880x1536",
        "tags": [
          "preview",
          "tiled",
          "retina"
        ],
        "uri": "tmnobhhya_PopupTiled_2880.png"
      },
      {
        "contentLength": 19771923,
        "resolution": "3840x2160",
        "tags": [
          "preview",
          "tiled",
          "retina"
        ],
        "uri": "tmnobhhya_PopupTiled_3840.png"
      },
      {
        "contentLength": 2632392,
        "resolution": "1440x768",
        "tags": [
          "preview"
        ],
        "uri": "tmnobhhya_Popup_1440.png"
      },
      {
        "contentLength": 4908533,
        "resolution": "1920x1080",
        "tags": [
          "preview"
        ],
        "uri": "tmnobhhya_Popup_1920.png"
      },
      {
        "contentLength": 10458993,
        "resolution": "2880x1536",
        "tags": [
          "preview",
          "retina"
        ],
        "uri": "tmnobhhya_Popup_2880.png"
      },
      {
        "contentLength": 20009538,
        "resolution": "3840x2160",
        "tags": [
          "preview",
          "retina"
        ],
        "uri": "tmnobhhya_Popup_3840.png"
      }
    ],
    "relativeSize": "1x1",
    "scaleReferences": []
  },
  "process_date": "2024-04-17 06:52:12",
  "properties": [],
  "referencePreviews": {
    "maps": [],
    "models": []
  },
  "references": [],
  "revised": false,
  "revision": 0,
  "semanticTags": {
    "3d_mesh": [],
    "architectural_style": {},
    "asset_type": "surface",
    "contains": [
      "metal",
      "sheet",
      "door",
      "steel",
      "shutter"
    ],
    "descriptive": [
      "clean",
      " galvanized",
      " grooved"
    ],
    "environment": [
      "urban",
      "industrial"
    ],
    "industry": [
      "archviz",
      "games",
      "VFX"
    ],
    "interior_exterior": [
      "exterior"
    ],
    "latin_name": [],
    "locations": {
      "Europe": {
        "United Kingdom": {}
      }
    },
    "maxSize": 2,
    "minSize": 2,
    "name": "Garage Door",
    "orientation": [
      "wall"
    ],
    "resolution": 8192,
    "season": [],
    "state": [
      "old"
    ],
    "subject_matter": "manmade",
    "theme": [
      "garage",
      " house",
      " urban",
      " city",
      " house"
    ]
  },
  "tags": [
    "uk",
    "galvanized",
    "steel",
    "roller",
    "shutter",
    "archviz"
  ],
  "texelDensity": 4096,
  "texture_type": "basic",
  "ue_plugin_archives": [
    {
      "contentLength": 248140470,
      "gltfVersion": "2.0",
      "tier": 0,
      "type": "gltf",
      "uri": "ue_plugin_archives/tier_0/tmnobhhya_tier_0.zip",
      "version": 1
    },
    {
      "contentLength": 77096711,
      "gltfVersion": "2.0",
      "tier": 1,
      "type": "gltf",
      "uri": "ue_plugin_archives/tier_1/tmnobhhya_tier_1.zip",
      "version": 1
    },
    {
      "contentLength": 19995792,
      "gltfVersion": "2.0",
      "tier": 2,
      "type": "gltf",
      "uri": "ue_plugin_archives/tier_2/tmnobhhya_tier_2.zip",
      "version": 1
    },
    {
      "contentLength": 1551701,
      "gltfVersion": "2.0",
      "tier": 3,
      "type": "gltf",
      "uri": "ue_plugin_archives/tier_3/tmnobhhya_tier_3.zip",
      "version": 1
    }
  ],
  "version": 2
}